{
  "posts": [
    {
      "title": "JavaScript is Amazing",
      "body": "I love programming in javascript. It's amazing.",
      "id": 1
    },
    {
      "title": "I love programming.",
      "body": "I enjoy programming. You can code anything that comes in your mind, oh! except coding an actual live human being, that'll be cool. Hope someone manages to create it.",
      "id": 2
    },
    {
      "title": "Python Rocks",
      "body": "The best programming in the world. Python rocks.",
      "id": 3
    }
  ]
}